{
    "auto_devops_enabled": "false",
    "avatar": null,
    "avatar_hash": null,
    "default_branch_protection": 2,
    "description": "Managed via IaC",
    "emails_disabled": true,
    "extra_shared_runners_minutes_limit": 0,
    "ip_restriction": [],
    "lfs_enabled": false,
    "membership_lock": true,
    "mentions_disabled": true,
    "prevent_forking_outside_group": true,
    "project_creation_level": "noone",
    "push_rules": {
        "author_email_regex": "@example.com",
        "branch_name_regex": "(feature|hotfix)\/*",
        "commit_committer_check": true,
        "commit_message_regex": null,
        "deny_delete_tag": true,
        "file_name_regex": "(jar|exe)$",
        "max_file_size": 50,
        "member_check": true,
        "prevent_secrets": true,
        "reject_unsigned_commits": false
    },
    "request_access_enabled": false,
    "share_with_group_lock": true,
    "shared_runners_minutes_limit": 0,
    "shared_runners_setting": "enabled",
    "subgroup_cretion_level": "owner",
    "two_factor_grace_period": 0,
    "visibility_level": "private",
    "wiki_access_level": "disabled"
}